pysource_minimize/__init__.py
pysource_minimize/__main__.py
pysource_minimize/_minimize.py
pysource_minimize/_minimize_base.py
pysource_minimize/_minimize_structure.py
pysource_minimize/_minimize_unique_name.py
pysource_minimize/_minimize_value.py
pysource_minimize/_utils.py
pysource_minimize/py.typed
pysource_minimize-0.10.1.dist-info/METADATA
pysource_minimize-0.10.1.dist-info/WHEEL
pysource_minimize-0.10.1.dist-info/entry_points.txt
pysource_minimize-0.10.1.dist-info/licenses/LICENSE
pysource_minimize-0.10.1.dist-info/RECORD
