Metadata-Version: 2.4
Name: pysource-minimize
Version: 0.10.1
Summary: minimize python source code
Project-URL: Documentation, https://github.com/15r10nk/pysource-minimize#readme
Project-URL: Issues, https://github.com/15r10nk/pysource-minimize/issues
Project-URL: Source, https://github.com/15r10nk/pysource-minimize
Author-email: Frank Hoffmann <15r10nk@polarbit.de>
License-Expression: MIT
License-File: LICENSE
Classifier: Development Status :: 4 - Beta
Classifier: Programming Language :: Python
Classifier: Programming Language :: Python :: 3.8
Classifier: Programming Language :: Python :: 3.9
Classifier: Programming Language :: Python :: 3.10
Classifier: Programming Language :: Python :: 3.11
Classifier: Programming Language :: Python :: 3.12
Classifier: Programming Language :: Python :: 3.13
Classifier: Programming Language :: Python :: Implementation :: CPython
Classifier: Programming Language :: Python :: Implementation :: PyPy
Requires-Python: >=3.8
Requires-Dist: astunparse>=1.6.3; python_version < '3.9'
Provides-Extra: cli
Requires-Dist: black>=23.3.0; extra == 'cli'
Requires-Dist: click>=8.1.7; extra == 'cli'
Requires-Dist: rich>=12.6.0; extra == 'cli'
